{
    "friendships": [
        {
            "id": "65e10aa151001",
            "userId1": "65e10aa11a001",
            "userId2": "65e10aa11a002"
        },
        {
            "id": "65e10aa151002",
            "userId1": "65e10aa11a003",
            "userId2": "65e10aa11a004"
        },
        {
            "id": "65e10aa151003",
            "userId1": "65e10aa11a005",
            "userId2": "65e10aa11a006"
        },
        {
            "id": "65e10aa151004",
            "userId1": "65e10aa11a007",
            "userId2": "65e10aa11a008"
        },
        {
            "id": "65e10aa151005",
            "userId1": "65e10aa11a009",
            "userId2": "65e10aa11a00a"
        },
        {
            "id": "65f3dd151001",
            "userId1": "65f3aa11a001",
            "userId2": "65f3aa11a002"
        },
        {
            "id": "65f3dd151002",
            "userId1": "65f3aa11a001",
            "userId2": "65f3aa11a006"
        },
        {
            "id": "65f3dd151003",
            "userId1": "65f3aa11a001",
            "userId2": "65f3aa11a00f"
        },
        {
            "id": "65f3dd151004",
            "userId1": "65f3aa11a002",
            "userId2": "65f3aa11a003"
        },
        {
            "id": "65f3dd151005",
            "userId1": "65f3aa11a002",
            "userId2": "65f3aa11a004"
        },
        {
            "id": "65f3dd151006",
            "userId1": "65f3aa11a003",
            "userId2": "65f3aa11a009"
        },
        {
            "id": "65f3dd151007",
            "userId1": "65f3aa11a003",
            "userId2": "65f3aa11a010"
        },
        {
            "id": "65f3dd151008",
            "userId1": "65f3aa11a004",
            "userId2": "65f3aa11a009"
        },
        {
            "id": "65f3dd151009",
            "userId1": "65f3aa11a004",
            "userId2": "65f3aa11a01e"
        },
        {
            "id": "65f3dd15100a",
            "userId1": "65f3aa11a005",
            "userId2": "65f3aa11a006"
        },
        {
            "id": "65f3dd15100b",
            "userId1": "65f3aa11a005",
            "userId2": "65f3aa11a007"
        },
        {
            "id": "65f3dd15100c",
            "userId1": "65f3aa11a006",
            "userId2": "65f3aa11a012"
        },
        {
            "id": "65f3dd15100d",
            "userId1": "65f3aa11a006",
            "userId2": "65f3aa11a01e"
        },
        {
            "id": "65f3dd15100e",
            "userId1": "65f3aa11a007",
            "userId2": "65f3aa11a008"
        },
        {
            "id": "65f3dd15100f",
            "userId1": "65f3aa11a007",
            "userId2": "65f3aa11a010"
        },
        {
            "id": "65f3dd151010",
            "userId1": "65f3aa11a008",
            "userId2": "65f3aa11a014"
        },
        {
            "id": "65f3dd151011",
            "userId1": "65f3aa11a008",
            "userId2": "65f3aa11a01a"
        },
        {
            "id": "65f3dd151012",
            "userId1": "65f3aa11a009",
            "userId2": "65f3aa11a00a"
        },
        {
            "id": "65f3dd151013",
            "userId1": "65f3aa11a009",
            "userId2": "65f3aa11a01b"
        },
        {
            "id": "65f3dd151014",
            "userId1": "65f3aa11a00a",
            "userId2": "65f3aa11a01b"
        },
        {
            "id": "65f3dd151015",
            "userId1": "65f3aa11a00a",
            "userId2": "65f3aa11a01d"
        },
        {
            "id": "65f3dd151016",
            "userId1": "65f3aa11a00b",
            "userId2": "65f3aa11a00c"
        },
        {
            "id": "65f3dd151017",
            "userId1": "65f3aa11a00b",
            "userId2": "65f3aa11a015"
        },
        {
            "id": "65f3dd151018",
            "userId1": "65f3aa11a00c",
            "userId2": "65f3aa11a016"
        },
        {
            "id": "65f3dd151019",
            "userId1": "65f3aa11a00c",
            "userId2": "65f3aa11a01e"
        },
        {
            "id": "65f3dd15101a",
            "userId1": "65f3aa11a00d",
            "userId2": "65f3aa11a00e"
        },
        {
            "id": "65f3dd15101b",
            "userId1": "65f3aa11a00d",
            "userId2": "65f3aa11a016"
        },
        {
            "id": "65f3dd15101c",
            "userId1": "65f3aa11a00e",
            "userId2": "65f3aa11a017"
        },
        {
            "id": "65f3dd15101d",
            "userId1": "65f3aa11a00e",
            "userId2": "65f3aa11a01c"
        },
        {
            "id": "65f3dd15101e",
            "userId1": "65f3aa11a00f",
            "userId2": "65f3aa11a011"
        },
        {
            "id": "65f3dd15101f",
            "userId1": "65f3aa11a00f",
            "userId2": "65f3aa11a013"
        },
        {
            "id": "65f3dd151020",
            "userId1": "65f3aa11a010",
            "userId2": "65f3aa11a011"
        },
        {
            "id": "65f3dd151021",
            "userId1": "65f3aa11a010",
            "userId2": "65f3aa11a014"
        },
        {
            "id": "65f3dd151022",
            "userId1": "65f3aa11a011",
            "userId2": "65f3aa11a01a"
        },
        {
            "id": "65f3dd151023",
            "userId1": "65f3aa11a011",
            "userId2": "65f3aa11a01e"
        },
        {
            "id": "65f3dd151024",
            "userId1": "65f3aa11a012",
            "userId2": "65f3aa11a013"
        },
        {
            "id": "65f3dd151025",
            "userId1": "65f3aa11a012",
            "userId2": "65f3aa11a017"
        },
        {
            "id": "65f3dd151026",
            "userId1": "65f3aa11a013",
            "userId2": "65f3aa11a018"
        },
        {
            "id": "65f3dd151027",
            "userId1": "65f3aa11a013",
            "userId2": "65f3aa11a01d"
        },
        {
            "id": "65f3dd151028",
            "userId1": "65f3aa11a014",
            "userId2": "65f3aa11a01a"
        },
        {
            "id": "65f3dd151029",
            "userId1": "65f3aa11a014",
            "userId2": "65f3aa11a01e"
        },
        {
            "id": "65f3dd15102a",
            "userId1": "65f3aa11a015",
            "userId2": "65f3aa11a018"
        },
        {
            "id": "65f3dd15102b",
            "userId1": "65f3aa11a015",
            "userId2": "65f3aa11a01d"
        },
        {
            "id": "65f3dd15102c",
            "userId1": "65f3aa11a016",
            "userId2": "65f3aa11a01b"
        },
        {
            "id": "65f3dd15102d",
            "userId1": "65f3aa11a016",
            "userId2": "65f3aa11a01e"
        },
        {
            "id": "65f3dd15102e",
            "userId1": "65f3aa11a017",
            "userId2": "65f3aa11a01d"
        },
        {
            "id": "65f3dd15102f",
            "userId1": "65f3aa11a018",
            "userId2": "65f3aa11a01c"
        },
        {
            "id": "65f900151001",
            "userId1": "699dab0435090",
            "userId2": "65e10aa11a001"
        },
        {
            "id": "65f900151002",
            "userId1": "65e10aa11a009",
            "userId2": "65f3aa11a001"
        },
        {
            "id": "65f900151003",
            "userId1": "699dab0435090",
            "userId2": "65f3aa11a002"
        },
        {
            "id": "65f900151004",
            "userId1": "65e10aa11a009",
            "userId2": "65e10aa11a001"
        },
        {
            "id": "65fc00151001",
            "userId1": "65e10aa11a009",
            "userId2": "699dab0435090"
        },
        {
            "id": "65fc00151002",
            "userId1": "65f3aa11a001",
            "userId2": "65f3aa11a002" 
        },
        {
            "id": "65fc00151003",
            "userId1": "65e10aa11a001",
            "userId2": "65f3bb11b00a" 
        },
        {
            "id": "65fc00151004",
            "userId1": "65e10aa11a009", 
            "userId2": "65f3bb11b00a" 
        },
        {
            "id": "65fc00151005",
            "userId1": "699dab0435090",
            "userId2": "65f3aa11a001"
        },
        {
            "id": "65fc00151006",
            "userId1": "65f3aa11a002",
            "userId2": "65e10aa11a001" 
        },
        {
            "id": "65fc00151007",
            "userId1": "65f3bb11b00a",
            "userId2": "65f3aa11a001" 
        },
        {
            "id": "65fc00151008",
            "userId1": "699dab0435090",
            "userId2": "65e10aa11a009" 
        }
    ]
}